[
    {
        "id": "78",
        "question": "In a group of 10 people, 1 like Physics, 10 like Maths, and 1 like both. How many people like Physics only?",
        "options": [
            3,
            2,
            1,
            0
        ],
        "correct": 0
    },
    {
        "id": "46",
        "question": "In a group of 10 people, 9 like Physics, 8 like Maths, and 7 like both. How many people like Physics only?",
        "options": [
            1,
            2,
            5,
            2
        ],
        "correct": 2
    },
    {
        "id": "64",
        "question": "In a group of 10 people, 6 like Physics, 10 like Maths, and 6 like both. How many people like Physics only?",
        "options": [
            0,
            6,
            5,
            1
        ],
        "correct": 0
    },
    {
        "id": "34",
        "question": "In a group of 10 people, 6 like Physics, 8 like Maths, and 4 like both. How many people like Physics only?",
        "options": [
            1,
            2,
            5,
            9
        ],
        "correct": 2
    },
    {
        "id": "20",
        "question": "The initial value was 3, and the new value is 8. What is the percentage change?",
        "options": [
            172.0,
            166.0,
            167.0,
            173.0
        ],
        "correct": 167.0
    },
    {
        "id": "85",
        "question": "The initial value was 5, and the new value is 4. What is the percentage change?",
        "options": [
            -20.0,
            -23.0,
            -11.0,
            -15.0
        ],
        "correct": -20.0
    },
    {
        "id": "90",
        "question": "The initial value was 10, and the new value is 8. What is the percentage change?",
        "options": [
            -18.0,
            -24.0,
            -13.0,
            -20.0
        ],
        "correct": -20.0
    },
    {
        "id": "58",
        "question": "An athlete's chances of qualifying for the Highland Games changed from 1% to 3%. What is the absolute percentage change and the relative percentage change?",
        "options": [
            "Absolute: 2%, Relative: 200.0%",
            "Absolute: 5%, Relative: 220.0%",
            "Absolute: 0%, Relative: 193.0%",
            "Absolute: 5%, Relative: 218.0%"
        ],
        "correct": "Absolute: 2%, Relative: 200.0%"
    },
    {
        "id": "78",
        "question": "An athlete's chances of qualifying for the Highland Games changed from 1% to 6%. What is the absolute percentage change and the relative percentage change?",
        "options": [
            "Absolute: 3%, Relative: 495.0%",
            "Absolute: 5%, Relative: 500.0%",
            "Absolute: 8%, Relative: 516.0%",
            "Absolute: 7%, Relative: 516.0%"
        ],
        "correct": "Absolute: 5%, Relative: 500.0%"
    },
    {
        "id": "84",
        "question": "If it takes 6 machines 10 minutes to make 7 crackers, how long would it take 60 machines to make 35 crackers?",
        "options": [
            "9.08 minutes",
            "5.0 minutes",
            "6.14 minutes",
            "4.49 minutes",
            "10.00 minutes"
        ],
        "correct": "5.0 minutes"
    },
    {
        "id": "100",
        "question": "If it takes 5 machines 3 minutes to make 12 crackers, how long would it take 50 machines to make 48 crackers?",
        "options": [
            "0.00 minutes",
            "1.2 minutes",
            "2.40 minutes",
            "3.93 minutes",
            "3.62 minutes"
        ],
        "correct": "1.2 minutes"
    }
]