[
    {
        "id": "5",
        "question": "In a group of 10 people, 10 like Physics, 7 like Maths, and 7 like both. How many people like Physics only?",
        "options": [
            5,
            8,
            2,
            3
        ],
        "correct": 3
    },
    {
        "id": "60",
        "question": "In a group of 10 people, 10 like Physics, 5 like Maths, and 5 like both. How many people like Physics only?",
        "options": [
            5,
            3,
            3,
            2
        ],
        "correct": 5
    },
    {
        "id": "1",
        "question": "In a group of 10 people, 4 like Physics, 10 like Maths, and 4 like both. How many people like Physics only?",
        "options": [
            6,
            3,
            0,
            4
        ],
        "correct": 0
    },
    {
        "id": "65",
        "question": "In a group of 10 people, 7 like Physics, 5 like Maths, and 2 like both. How many people like Physics only?",
        "options": [
            9,
            9,
            6,
            5
        ],
        "correct": 5
    },
    {
        "id": "46",
        "question": "The initial value was 2, and the new value is 8. What is the percentage change?",
        "options": [
            300.0,
            310.0,
            299.0,
            303.0
        ],
        "correct": 300.0
    },
    {
        "id": "69",
        "question": "The initial value was 4, and the new value is 1. What is the percentage change?",
        "options": [
            -73.0,
            -75.0,
            -70.0,
            -78.0
        ],
        "correct": -75.0
    },
    {
        "id": "49",
        "question": "The initial value was 4, and the new value is 9. What is the percentage change?",
        "options": [
            123.0,
            132.0,
            125.0,
            130.0
        ],
        "correct": 125.0
    },
    {
        "id": "68",
        "question": "An athlete's chances of qualifying for the Highland Games changed from 5% to 6%. What is the absolute percentage change and the relative percentage change?",
        "options": [
            "Absolute: 3%, Relative: 38.0%",
            "Absolute: -1%, Relative: 11.0%",
            "Absolute: 1%, Relative: 20.0%",
            "Absolute: 4%, Relative: 30.0%"
        ],
        "correct": "Absolute: 1%, Relative: 20.0%"
    },
    {
        "id": "44",
        "question": "An athlete's chances of qualifying for the Highland Games changed from 10% to 7%. What is the absolute percentage change and the relative percentage change?",
        "options": [
            "Absolute: 5%, Relative: 43.0%",
            "Absolute: 2%, Relative: 20.0%",
            "Absolute: 3%, Relative: 30.0%",
            "Absolute: 5%, Relative: 51.0%"
        ],
        "correct": "Absolute: 3%, Relative: 30.0%"
    },
    {
        "id": "67",
        "question": "If it takes 5 machines 5 minutes to make 12 crackers, how long would it take 50 machines to make 48 crackers?",
        "options": [
            "6.00 minutes",
            "6.02 minutes",
            "1.25 minutes",
            "2.97 minutes",
            "2.0 minutes"
        ],
        "correct": "2.0 minutes"
    },
    {
        "id": "54",
        "question": "If it takes 6 machines 10 minutes to make 11 crackers, how long would it take 60 machines to make 22 crackers?",
        "options": [
            "2.0 minutes",
            "4.67 minutes",
            "1.22 minutes",
            "4.00 minutes",
            "2.82 minutes"
        ],
        "correct": "2.0 minutes"
    }
]