[
    {
        "id": "88",
        "question": "In a group of 10 people, 10 like Physics, 2 like Maths, and 2 like both. How many people like Physics only?",
        "options": [
            8,
            5,
            1,
            6
        ],
        "correct": 8
    },
    {
        "id": "40",
        "question": "In a group of 10 people, 8 like Physics, 8 like Maths, and 6 like both. How many people like Physics only?",
        "options": [
            5,
            9,
            2,
            8
        ],
        "correct": 2
    },
    {
        "id": "32",
        "question": "In a group of 10 people, 9 like Physics, 7 like Maths, and 6 like both. How many people like Physics only?",
        "options": [
            10,
            3,
            6,
            3
        ],
        "correct": 3
    },
    {
        "id": "95",
        "question": "In a group of 10 people, 6 like Physics, 9 like Maths, and 5 like both. How many people like Physics only?",
        "options": [
            1,
            7,
            4,
            2
        ],
        "correct": 1
    },
    {
        "id": "84",
        "question": "The initial value was 3, and the new value is 7. What is the percentage change?",
        "options": [
            138.0,
            134.0,
            132.0,
            133.0
        ],
        "correct": 133.0
    },
    {
        "id": "65",
        "question": "The initial value was 5, and the new value is 8. What is the percentage change?",
        "options": [
            64.0,
            66.0,
            59.0,
            60.0
        ],
        "correct": 60.0
    },
    {
        "id": "77",
        "question": "The initial value was 1, and the new value is 1. What is the percentage change?",
        "options": [
            0.0,
            5.0,
            -3.0,
            5.0
        ],
        "correct": 0.0
    },
    {
        "id": "40",
        "question": "An athlete's chances of qualifying for the Highland Games changed from 6% to 9%. What is the absolute percentage change and the relative percentage change?",
        "options": [
            "Absolute: 3%, Relative: 50.0%",
            "Absolute: 5%, Relative: 69.0%",
            "Absolute: 1%, Relative: 41.0%",
            "Absolute: 5%, Relative: 74.0%"
        ],
        "correct": "Absolute: 3%, Relative: 50.0%"
    },
    {
        "id": "65",
        "question": "An athlete's chances of qualifying for the Highland Games changed from 4% to 3%. What is the absolute percentage change and the relative percentage change?",
        "options": [
            "Absolute: 1%, Relative: 25.0%",
            "Absolute: -1%, Relative: 16.0%",
            "Absolute: 3%, Relative: 41.0%",
            "Absolute: 3%, Relative: 51.0%"
        ],
        "correct": "Absolute: 1%, Relative: 25.0%"
    },
    {
        "id": "89",
        "question": "If it takes 7 machines 4 minutes to make 18 crackers, how long would it take 70 machines to make 72 crackers?",
        "options": [
            "4.01 minutes",
            "3.20 minutes",
            "0.88 minutes",
            "5.27 minutes",
            "1.6 minutes"
        ],
        "correct": "1.6 minutes"
    },
    {
        "id": "73",
        "question": "If it takes 3 machines 10 minutes to make 11 crackers, how long would it take 30 machines to make 44 crackers?",
        "options": [
            "4.0 minutes",
            "8.08 minutes",
            "2.90 minutes",
            "5.62 minutes",
            "12.00 minutes"
        ],
        "correct": "4.0 minutes"
    }
]